deed/__init__.py
deed/audit_modes.py
deed/bottle_kit.py
deed/gdpr_utils.py
deed/tracing.py
deed-0.1.6.dist-info/METADATA
deed-0.1.6.dist-info/WHEEL
deed-0.1.6.dist-info/top_level.txt
deed-0.1.6.dist-info/RECORD
