Metadata-Version: 2.1
Name: deed
Version: 0.1.6
Summary: ActivityFormatter for object changes (auditlog)
Home-page: https://github.com/TruckPad/deed-py
Author: TruckPad
License: Apache License 2.0
Platform: UNKNOWN
Requires-Python: >= 2.7, !=3.0.*, !=3.1.*, !=3.2.*, !=3.3.*, !=3.4.*, !=3.5.*
Requires-Dist: jsonpatch (>=1.32)
